{
  "id": "tt0084805",
  "title": "Tootsie",
  "description": "Michael Dorsey, an unsuccessful actor, disguises himself as a woman in order to get a role on a trashy hospital soap.",
  "imageUrl": "https://m.media-amazon.com/images/M/MV5BMTY4MGJjMTktNGM4Ni00ODliLWJlYjQtNjc4NmY2NjQ3NzEzXkEyXkFqcGdeQXVyMTA0MjU0Ng@@._V1_UX140_CR0,0,140,209_AL_.jpg",
  "year": 1982,
  "certification": "PG",
  "runtime": 116,
  "genres": [
    "Comedy",
    "Drama",
    "Romance"
  ],
  "rating": 7.4,
  "metascore": 88
}